{
  "id": "2978739",
  "name": "book",
  "font_family": "iconfont",
  "css_prefix_text": "icon-",
  "description": "",
  "glyphs": [
    {
      "icon_id": "2019101",
      "name": "偷听",
      "font_class": "touting",
      "unicode": "e7c4",
      "unicode_decimal": 59332
    },
    {
      "icon_id": "7765161",
      "name": "家长_书架",
      "font_class": "jiachang_shujia",
      "unicode": "e65c",
      "unicode_decimal": 58972
    },
    {
      "icon_id": "1727378",
      "name": "33资源",
      "font_class": "ziyuan1",
      "unicode": "e8a4",
      "unicode_decimal": 59556
    },
    {
      "icon_id": "10564271",
      "name": "eye",
      "font_class": "eye",
      "unicode": "e706",
      "unicode_decimal": 59142
    },
    {
      "icon_id": "10564278",
      "name": "eye-none",
      "font_class": "eye-none",
      "unicode": "e709",
      "unicode_decimal": 59145
    },
    {
      "icon_id": "2675007",
      "name": "我的",
      "font_class": "wode",
      "unicode": "e630",
      "unicode_decimal": 58928
    },
    {
      "icon_id": "2675009",
      "name": "首页",
      "font_class": "shouye",
      "unicode": "e62e",
      "unicode_decimal": 58926
    },
    {
      "icon_id": "145438",
      "name": "搜索",
      "font_class": "sousuo",
      "unicode": "e62f",
      "unicode_decimal": 58927
    },
    {
      "icon_id": "398281",
      "name": "夜间模式",
      "font_class": "yejianmoshi",
      "unicode": "e633",
      "unicode_decimal": 58931
    },
    {
      "icon_id": "6010919",
      "name": "菜单",
      "font_class": "caidan",
      "unicode": "e614",
      "unicode_decimal": 58900
    },
    {
      "icon_id": "11372694",
      "name": "设置",
      "font_class": "shezhi",
      "unicode": "e8b7",
      "unicode_decimal": 59575
    },
    {
      "icon_id": "14718933",
      "name": "目录",
      "font_class": "mulu",
      "unicode": "e602",
      "unicode_decimal": 58882
    },
    {
      "icon_id": "24639346",
      "name": "晴天（白天）",
      "font_class": "a-qingtianbaitian",
      "unicode": "e6a2",
      "unicode_decimal": 59042
    }
  ]
}
